taskvine_report/__init__.py
taskvine_report/utils.py
taskvine_report/cli/__init__.py
taskvine_report/cli/parse.py
taskvine_report/cli/report.py
taskvine_report/routes/__init__.py
taskvine_report/routes/export_csv_files.py
taskvine_report/routes/file_concurrent_replicas.py
taskvine_report/routes/file_created_size.py
taskvine_report/routes/file_retention_time.py
taskvine_report/routes/file_sizes.py
taskvine_report/routes/file_transferred_size.py
taskvine_report/routes/lock.py
taskvine_report/routes/logger.py
taskvine_report/routes/runtime_state.py
taskvine_report/routes/runtime_template.py
taskvine_report/routes/task_completion_percentiles.py
taskvine_report/routes/task_concurrency.py
taskvine_report/routes/task_dependencies.py
taskvine_report/routes/task_dependents.py
taskvine_report/routes/task_execution_details.py
taskvine_report/routes/task_execution_time.py
taskvine_report/routes/task_response_time.py
taskvine_report/routes/task_retrieval_time.py
taskvine_report/routes/task_subgraphs.py
taskvine_report/routes/worker_concurrency.py
taskvine_report/routes/worker_executing_tasks.py
taskvine_report/routes/worker_lifetime.py
taskvine_report/routes/worker_storage_consumption.py
taskvine_report/routes/worker_transfers.py
taskvine_report/routes/worker_waiting_retrieval_tasks.py
taskvine_report/scripts/configs.py
taskvine_report/scripts/generate_ft_data.py
taskvine_report/scripts/get_dag_stats.py
taskvine_report/scripts/plot_file_storage_footprint.py
taskvine_report/scripts/plot_storage_consumption_peaks.py
taskvine_report/scripts/plot_storage_consumption_per_worker.py
taskvine_report/scripts/plot_task_completion_percentiles.py
taskvine_report/scripts/t.py
taskvine_report/src/__init__.py
taskvine_report/src/data_parser.py
taskvine_report/src/file_info.py
taskvine_report/src/manager_info.py
taskvine_report/src/task_info.py
taskvine_report/src/worker_info.py
taskvine_report/static/favicon.ico
taskvine_report/static/css/content.css
taskvine_report/static/css/header.css
taskvine_report_tool-2025.9.1.dist-info/licenses/COPYING
taskvine_report_tool-2025.9.1.dist-info/METADATA
taskvine_report_tool-2025.9.1.dist-info/WHEEL
taskvine_report_tool-2025.9.1.dist-info/entry_points.txt
taskvine_report_tool-2025.9.1.dist-info/top_level.txt
taskvine_report_tool-2025.9.1.dist-info/RECORD
