Metadata-Version: 2.4
Name: taskvine-report-tool
Version: 2025.9.1
Summary: Visualization and analysis tool for TaskVine execution logs
Home-page: https://github.com/cooperative-computing-lab/taskvine-report-tool
Author: Collaborative Computing Lab (CCL), University of Notre Dame
Author-email: jzhou24@nd.edu
Project-URL: Documentation, https://ccl.cse.nd.edu/software/taskvine/
Project-URL: Repository, https://github.com/cooperative-computing-lab/taskvine-report-tool
Project-URL: Bug Reports, https://github.com/cooperative-computing-lab/taskvine-report-tool/issues
Project-URL: CCL Homepage, https://ccl.cse.nd.edu/
Keywords: taskvine,workflow,visualization,monitoring,distributed-computing,ccl,notre-dame
Classifier: Development Status :: 4 - Beta
Classifier: Intended Audience :: Developers
Classifier: Intended Audience :: Science/Research
Classifier: Operating System :: OS Independent
Classifier: Programming Language :: Python :: 3
Classifier: Programming Language :: Python :: 3.7
Classifier: Programming Language :: Python :: 3.8
Classifier: Programming Language :: Python :: 3.9
Classifier: Programming Language :: Python :: 3.10
Classifier: Programming Language :: Python :: 3.11
Classifier: Programming Language :: Python :: 3.12
Classifier: Programming Language :: Python :: 3.13
Classifier: Topic :: Scientific/Engineering
Classifier: Topic :: System :: Distributed Computing
Classifier: Topic :: System :: Monitoring
Requires-Python: >=3.7
License-File: COPYING
Requires-Dist: flask
Requires-Dist: pandas
Requires-Dist: cloudpickle
Requires-Dist: tqdm
Requires-Dist: bitarray
Requires-Dist: pytz
Requires-Dist: graphviz
Requires-Dist: rich
Requires-Dist: polars
Requires-Dist: numpy
Requires-Dist: pyarrow
Provides-Extra: dev
Requires-Dist: pytest; extra == "dev"
Requires-Dist: pytest-cov; extra == "dev"
Requires-Dist: black; extra == "dev"
Requires-Dist: flake8; extra == "dev"
Requires-Dist: mypy; extra == "dev"
Provides-Extra: test
Requires-Dist: pytest; extra == "test"
Requires-Dist: pytest-cov; extra == "test"
Dynamic: author
Dynamic: author-email
Dynamic: classifier
Dynamic: description
Dynamic: description-content-type
Dynamic: home-page
Dynamic: keywords
Dynamic: license-file
Dynamic: project-url
Dynamic: provides-extra
Dynamic: requires-dist
Dynamic: requires-python
Dynamic: summary
